tests/__init__.py
tests/test_processing.py
proj_img-0.1.0.dist-info/LICENSE
proj_img-0.1.0.dist-info/METADATA
proj_img-0.1.0.dist-info/WHEEL
proj_img-0.1.0.dist-info/top_level.txt
proj_img-0.1.0.dist-info/RECORD
