Metadata-Version: 2.1
Name: proj_img
Version: 0.1.0
Summary: A simple image processing package
Home-page: https://github.com/leopxz/processamento_de_imagens
Author: leopxz
Author-email: pxleonarddo@gmail.com
Classifier: Programming Language :: Python :: 3
Classifier: License :: OSI Approved :: MIT License
Classifier: Operating System :: OS Independent
Requires-Python: >=3.6
License-File: LICENSE
Requires-Dist: numpy
Requires-Dist: pillow
Requires-Dist: opencv-python
